tgclient/__init__.py
tgclient/client.py
tgclient-1.5.3.dist-info/LICENSE
tgclient-1.5.3.dist-info/METADATA
tgclient-1.5.3.dist-info/WHEEL
tgclient-1.5.3.dist-info/top_level.txt
tgclient-1.5.3.dist-info/RECORD
