Metadata-Version: 2.1
Name: tgclient
Version: 1.5.3
Summary: Telegram Bot Api Client
Home-page: https://github.com/amir1379/tgclient
Author: amirhossein faridvand
Author-email: amirfaridvand@gmail.com
License: GPL2
Keywords: telegram bot api
Platform: UNKNOWN
Classifier: Programming Language :: Python :: 3
Requires-Dist: urllib3
Requires-Dist: requests
Requires-Dist: flask
